odoo/addons/beesdoo_pos_coop_status/README.rst
odoo/addons/beesdoo_pos_coop_status/__init__.py
odoo/addons/beesdoo_pos_coop_status/__manifest__.py
odoo/addons/beesdoo_pos_coop_status/readme/CONTRIBUTORS.rst
odoo/addons/beesdoo_pos_coop_status/readme/DESCRIPTION.rst
odoo/addons/beesdoo_pos_coop_status/static/description/index.html
odoo/addons/beesdoo_pos_coop_status/static/src/css/coop_status.css
odoo/addons/beesdoo_pos_coop_status/static/src/js/models.js
odoo/addons/beesdoo_pos_coop_status/static/src/js/screens.js
odoo/addons/beesdoo_pos_coop_status/static/src/xml/pos.xml
odoo/addons/beesdoo_pos_coop_status/views/assets.xml
odoo12_addon_beesdoo_pos_coop_status-12.0.1.0.0.99.dev5.dist-info/METADATA
odoo12_addon_beesdoo_pos_coop_status-12.0.1.0.0.99.dev5.dist-info/WHEEL
odoo12_addon_beesdoo_pos_coop_status-12.0.1.0.0.99.dev5.dist-info/top_level.txt
odoo12_addon_beesdoo_pos_coop_status-12.0.1.0.0.99.dev5.dist-info/RECORD
