Metadata-Version: 2.1
Name: odoo12-addon-beesdoo-pos-coop-status
Version: 12.0.1.0.0.99.dev5
Summary: POS Support for cooperator status.
Home-page: https://coopiteasy.be
Author: Coop IT Easy SCRLfs
License: AGPL-3
Platform: UNKNOWN
Classifier: Programming Language :: Python
Classifier: Framework :: Odoo
Classifier: Framework :: Odoo :: 12.0
Classifier: License :: OSI Approved :: GNU Affero General Public License v3
Requires-Python: >=3.5
Requires-Dist: odoo12-addon-beesdoo-pos
Requires-Dist: odoo12-addon-beesdoo-shift
Requires-Dist: odoo (<12.1dev,>=12.0a)
